{
	"configurations" : 
	[
		{
			"directories" : 
			[
				{
					"build" : ".",
					"jsonFile" : "directory-.-f5ebdc15457944623624.json",
					"minimumCMakeVersion" : 
					{
						"string" : "3.10"
					},
					"projectIndex" : 0,
					"source" : ".",
					"targetIndexes" : 
					[
						0
					]
				}
			],
			"name" : "",
			"projects" : 
			[
				{
					"directoryIndexes" : 
					[
						0
					],
					"name" : "SFML_Test",
					"targetIndexes" : 
					[
						0
					]
				}
			],
			"targets" : 
			[
				{
					"directoryIndex" : 0,
					"id" : "SFML_Test::@6890427a1f51a3e7e1df",
					"jsonFile" : "target-SFML_Test-4ea515946e79a812920d.json",
					"name" : "SFML_Test",
					"projectIndex" : 0
				}
			]
		}
	],
	"kind" : "codemodel",
	"paths" : 
	{
		"build" : "/mnt/gamessd/Engine/build",
		"source" : "/mnt/gamessd/Engine"
	},
	"version" : 
	{
		"major" : 2,
		"minor" : 7
	}
}
